setup.cfg
setup.py
bin/w1-api
bin/w1-therm
w1/__init__.py
w1/consts.py
w1/device.py
w1/families.py
w1/manager.py
w1/master.py
w1/slave.py
w1/therm.py
w1.egg-info/PKG-INFO
w1.egg-info/SOURCES.txt
w1.egg-info/dependency_links.txt
w1.egg-info/top_level.txt