Metadata-Version: 1.0
Name: w1
Version: 0.3.0
Summary: Python wrapper for 1-wire Linux interface
Home-page: https://github.com/krzysztof-magosa/w1-python
Author: Krzysztof Magosa
Author-email: krzysztof@magosa.pl
License: MIT
Platform: UNKNOWN
